<error>
<domain>STATIC_C</domain>
<lang>C++</lang>
<checker>SIZEOF_MISMATCH</checker>
<type>sizeof_mismatch</type>
<subtype>wrong_sizeof</subtype>
<file>/Users/dylanm/Projects/proftpd-1.3.5/src/dirtree.c</file>
<function>pr_config_set_id</function>
<score>100</score>
<ordered>false</ordered>
<event>
<main>true</main>
<tag>suspicious_sizeof</tag>
<description>{CovLStrv2{{t{Passing argument {0} of type {1} and argument {2} to function {3} is suspicious.}{{code{ptr}}}{{code{unsigned int *}}}{{code{8UL /* sizeof (unsigned int *) */}}}{{code{pr_table_add}}}}}}</description>
<line>3821</line>
</event>
<event>
<remediation>true</remediation>
<tag>remediation</tag>
<description>{CovLStrv2{{t{Did you intend to use {0} instead of {1}?}{{code{sizeof (unsigned int)}}}{{code{sizeof (unsigned int *)}}}}}}</description>
<line>3821</line>
</event>
<extra>pr_table_add</extra>
<subcategory>wrong_sizeof</subcategory>
</error>
<error>
<domain>STATIC_C</domain>
<lang>C++</lang>
<checker>SIZEOF_MISMATCH</checker>
<type>sizeof_mismatch</type>
<subtype>wrong_sizeof</subtype>
<file>/Users/dylanm/Projects/proftpd-1.3.5/src/netio.c</file>
<function>pr_netio_open</function>
<score>100</score>
<ordered>false</ordered>
<event>
<main>true</main>
<tag>suspicious_sizeof</tag>
<description>{CovLStrv2{{t{Passing argument {0} of type {1} and argument {2} to function {3} is suspicious.}{{code{ctrl_netio}}}{{code{pr_netio_t *}}}{{code{8UL /* sizeof (pr_netio_t *) */}}}{{code{pr_table_add}}}}}}</description>
<line>474</line>
</event>
<event>
<remediation>true</remediation>
<tag>remediation</tag>
<description>{CovLStrv2{{t{Did you intend to use {0} instead of {1}?}{{code{sizeof (pr_netio_t)}}}{{code{sizeof (pr_netio_t *)}}}}}}</description>
<line>474</line>
</event>
<extra>pr_table_add</extra>
<subcategory>wrong_sizeof</subcategory>
</error>
<error>
<domain>STATIC_C</domain>
<lang>C++</lang>
<checker>SIZEOF_MISMATCH</checker>
<type>sizeof_mismatch</type>
<subtype>wrong_sizeof</subtype>
<file>/Users/dylanm/Projects/proftpd-1.3.5/src/netio.c</file>
<function>pr_netio_open</function>
<score>100</score>
<ordered>false</ordered>
<event>
<main>true</main>
<tag>suspicious_sizeof</tag>
<description>{CovLStrv2{{t{Passing argument {0} of type {1} and argument {2} to function {3} is suspicious.}{{code{default_ctrl_netio}}}{{code{pr_netio_t *}}}{{code{8UL /* sizeof (pr_netio_t *) */}}}{{code{pr_table_add}}}}}}</description>
<line>479</line>
</event>
<event>
<remediation>true</remediation>
<tag>remediation</tag>
<description>{CovLStrv2{{t{Did you intend to use {0} instead of {1}?}{{code{sizeof (pr_netio_t)}}}{{code{sizeof (pr_netio_t *)}}}}}}</description>
<line>479</line>
</event>
<extra>pr_table_add</extra>
<subcategory>wrong_sizeof</subcategory>
</error>
<error>
<domain>STATIC_C</domain>
<lang>C++</lang>
<checker>SIZEOF_MISMATCH</checker>
<type>sizeof_mismatch</type>
<subtype>wrong_sizeof</subtype>
<file>/Users/dylanm/Projects/proftpd-1.3.5/src/netio.c</file>
<function>pr_netio_open</function>
<score>100</score>
<ordered>false</ordered>
<event>
<main>true</main>
<tag>suspicious_sizeof</tag>
<description>{CovLStrv2{{t{Passing argument {0} of type {1} and argument {2} to function {3} is suspicious.}{{code{data_netio}}}{{code{pr_netio_t *}}}{{code{8UL /* sizeof (pr_netio_t *) */}}}{{code{pr_table_add}}}}}}</description>
<line>489</line>
</event>
<event>
<remediation>true</remediation>
<tag>remediation</tag>
<description>{CovLStrv2{{t{Did you intend to use {0} instead of {1}?}{{code{sizeof (pr_netio_t)}}}{{code{sizeof (pr_netio_t *)}}}}}}</description>
<line>489</line>
</event>
<extra>pr_table_add</extra>
<subcategory>wrong_sizeof</subcategory>
</error>
<error>
<domain>STATIC_C</domain>
<lang>C++</lang>
<checker>SIZEOF_MISMATCH</checker>
<type>sizeof_mismatch</type>
<subtype>wrong_sizeof</subtype>
<file>/Users/dylanm/Projects/proftpd-1.3.5/src/netio.c</file>
<function>pr_netio_open</function>
<score>100</score>
<ordered>false</ordered>
<event>
<main>true</main>
<tag>suspicious_sizeof</tag>
<description>{CovLStrv2{{t{Passing argument {0} of type {1} and argument {2} to function {3} is suspicious.}{{code{default_data_netio}}}{{code{pr_netio_t *}}}{{code{8UL /* sizeof (pr_netio_t *) */}}}{{code{pr_table_add}}}}}}</description>
<line>494</line>
</event>
<event>
<remediation>true</remediation>
<tag>remediation</tag>
<description>{CovLStrv2{{t{Did you intend to use {0} instead of {1}?}{{code{sizeof (pr_netio_t)}}}{{code{sizeof (pr_netio_t *)}}}}}}</description>
<line>494</line>
</event>
<extra>pr_table_add</extra>
<subcategory>wrong_sizeof</subcategory>
</error>
<error>
<domain>STATIC_C</domain>
<lang>C++</lang>
<checker>SIZEOF_MISMATCH</checker>
<type>sizeof_mismatch</type>
<subtype>wrong_sizeof</subtype>
<file>/Users/dylanm/Projects/proftpd-1.3.5/src/netio.c</file>
<function>pr_netio_open</function>
<score>100</score>
<ordered>false</ordered>
<event>
<main>true</main>
<tag>suspicious_sizeof</tag>
<description>{CovLStrv2{{t{Passing argument {0} of type {1} and argument {2} to function {3} is suspicious.}{{code{othr_netio}}}{{code{pr_netio_t *}}}{{code{8UL /* sizeof (pr_netio_t *) */}}}{{code{pr_table_add}}}}}}</description>
<line>504</line>
</event>
<event>
<remediation>true</remediation>
<tag>remediation</tag>
<description>{CovLStrv2{{t{Did you intend to use {0} instead of {1}?}{{code{sizeof (pr_netio_t)}}}{{code{sizeof (pr_netio_t *)}}}}}}</description>
<line>504</line>
</event>
<extra>pr_table_add</extra>
<subcategory>wrong_sizeof</subcategory>
</error>
<error>
<domain>STATIC_C</domain>
<lang>C++</lang>
<checker>SIZEOF_MISMATCH</checker>
<type>sizeof_mismatch</type>
<subtype>wrong_sizeof</subtype>
<file>/Users/dylanm/Projects/proftpd-1.3.5/src/netio.c</file>
<function>pr_netio_open</function>
<score>100</score>
<ordered>false</ordered>
<event>
<main>true</main>
<tag>suspicious_sizeof</tag>
<description>{CovLStrv2{{t{Passing argument {0} of type {1} and argument {2} to function {3} is suspicious.}{{code{default_othr_netio}}}{{code{pr_netio_t *}}}{{code{8UL /* sizeof (pr_netio_t *) */}}}{{code{pr_table_add}}}}}}</description>
<line>509</line>
</event>
<event>
<remediation>true</remediation>
<tag>remediation</tag>
<description>{CovLStrv2{{t{Did you intend to use {0} instead of {1}?}{{code{sizeof (pr_netio_t)}}}{{code{sizeof (pr_netio_t *)}}}}}}</description>
<line>509</line>
</event>
<extra>pr_table_add</extra>
<subcategory>wrong_sizeof</subcategory>
</error>
<error>
<domain>STATIC_C</domain>
<lang>C++</lang>
<checker>SIZEOF_MISMATCH</checker>
<type>sizeof_mismatch</type>
<subtype>sizeof_punning</subtype>
<file>/Users/dylanm/Projects/proftpd-1.3.5/modules/mod_core.c</file>
<function>core_sess_init</function>
<score>100</score>
<ordered>false</ordered>
<event>
<main>true</main>
<tag>suspicious_sizeof</tag>
<description>{CovLStrv2{{t{Passing argument {0} of type {1} and argument {2} to function {3} is suspicious.}{{code{&amp;session.xfer.total_bytes}}}{{code{off_t *}}}{{code{8UL /* sizeof (off_t *) */}}}{{code{pr_var_set}}}}{t{ In this case, {0} is equal to {1}, but this is not a portable assumption.}{{code{sizeof (off_t *)}}}{{code{sizeof (off_t)}}}}}}</description>
<line>5957</line>
</event>
<event>
<remediation>true</remediation>
<tag>remediation</tag>
<description>{CovLStrv2{{t{Did you intend to use {0} instead of {1}?}{{code{sizeof (off_t)}}}{{code{sizeof (off_t *)}}}}}}</description>
<line>5957</line>
</event>
<extra>pr_var_set</extra>
<subcategory>sizeof_punning</subcategory>
</error>
<error>
<domain>STATIC_C</domain>
<lang>C++</lang>
<checker>SIZEOF_MISMATCH</checker>
<type>sizeof_mismatch</type>
<subtype>sizeof_punning</subtype>
<file>/Users/dylanm/Projects/proftpd-1.3.5/modules/mod_core.c</file>
<function>core_sess_init</function>
<score>100</score>
<ordered>false</ordered>
<event>
<main>true</main>
<tag>suspicious_sizeof</tag>
<description>{CovLStrv2{{t{Passing argument {0} of type {1} and argument {2} to function {3} is suspicious.}{{code{&amp;session.total_bytes_in}}}{{code{off_t *}}}{{code{8UL /* sizeof (off_t *) */}}}{{code{pr_var_set}}}}{t{ In this case, {0} is equal to {1}, but this is not a portable assumption.}{{code{sizeof (off_t *)}}}{{code{sizeof (off_t)}}}}}}</description>
<line>5965</line>
</event>
<event>
<remediation>true</remediation>
<tag>remediation</tag>
<description>{CovLStrv2{{t{Did you intend to use {0} instead of {1}?}{{code{sizeof (off_t)}}}{{code{sizeof (off_t *)}}}}}}</description>
<line>5965</line>
</event>
<extra>pr_var_set</extra>
<subcategory>sizeof_punning</subcategory>
</error>
<error>
<domain>STATIC_C</domain>
<lang>C++</lang>
<checker>SIZEOF_MISMATCH</checker>
<type>sizeof_mismatch</type>
<subtype>sizeof_punning</subtype>
<file>/Users/dylanm/Projects/proftpd-1.3.5/modules/mod_core.c</file>
<function>core_sess_init</function>
<score>100</score>
<ordered>false</ordered>
<event>
<main>true</main>
<tag>suspicious_sizeof</tag>
<description>{CovLStrv2{{t{Passing argument {0} of type {1} and argument {2} to function {3} is suspicious.}{{code{&amp;session.total_bytes_out}}}{{code{off_t *}}}{{code{8UL /* sizeof (off_t *) */}}}{{code{pr_var_set}}}}{t{ In this case, {0} is equal to {1}, but this is not a portable assumption.}{{code{sizeof (off_t *)}}}{{code{sizeof (off_t)}}}}}}</description>
<line>5973</line>
</event>
<event>
<remediation>true</remediation>
<tag>remediation</tag>
<description>{CovLStrv2{{t{Did you intend to use {0} instead of {1}?}{{code{sizeof (off_t)}}}{{code{sizeof (off_t *)}}}}}}</description>
<line>5973</line>
</event>
<extra>pr_var_set</extra>
<subcategory>sizeof_punning</subcategory>
</error>
<error>
<domain>STATIC_C</domain>
<lang>C++</lang>
<checker>SIZEOF_MISMATCH</checker>
<type>sizeof_mismatch</type>
<subtype>sizeof_punning</subtype>
<file>/Users/dylanm/Projects/proftpd-1.3.5/modules/mod_core.c</file>
<function>core_sess_init</function>
<score>100</score>
<ordered>false</ordered>
<event>
<main>true</main>
<tag>suspicious_sizeof</tag>
<description>{CovLStrv2{{t{Passing argument {0} of type {1} and argument {2} to function {3} is suspicious.}{{code{&amp;session.total_bytes}}}{{code{off_t *}}}{{code{8UL /* sizeof (off_t *) */}}}{{code{pr_var_set}}}}{t{ In this case, {0} is equal to {1}, but this is not a portable assumption.}{{code{sizeof (off_t *)}}}{{code{sizeof (off_t)}}}}}}</description>
<line>5981</line>
</event>
<event>
<remediation>true</remediation>
<tag>remediation</tag>
<description>{CovLStrv2{{t{Did you intend to use {0} instead of {1}?}{{code{sizeof (off_t)}}}{{code{sizeof (off_t *)}}}}}}</description>
<line>5981</line>
</event>
<extra>pr_var_set</extra>
<subcategory>sizeof_punning</subcategory>
</error>
<error>
<domain>STATIC_C</domain>
<lang>C++</lang>
<checker>SIZEOF_MISMATCH</checker>
<type>sizeof_mismatch</type>
<subtype>wrong_sizeof</subtype>
<file>/Users/dylanm/Projects/proftpd-1.3.5/modules/mod_core.c</file>
<function>core_sess_init</function>
<score>100</score>
<ordered>false</ordered>
<event>
<main>true</main>
<tag>suspicious_sizeof</tag>
<description>{CovLStrv2{{t{Passing argument {0} of type {1} and argument {2} to function {3} is suspicious.}{{code{&amp;session.total_files_in}}}{{code{unsigned int *}}}{{code{8UL /* sizeof (unsigned int *) */}}}{{code{pr_var_set}}}}}}</description>
<line>5989</line>
</event>
<event>
<remediation>true</remediation>
<tag>remediation</tag>
<description>{CovLStrv2{{t{Did you intend to use {0} instead of {1}?}{{code{sizeof (unsigned int)}}}{{code{sizeof (unsigned int *)}}}}}}</description>
<line>5989</line>
</event>
<extra>pr_var_set</extra>
<subcategory>wrong_sizeof</subcategory>
</error>
<error>
<domain>STATIC_C</domain>
<lang>C++</lang>
<checker>SIZEOF_MISMATCH</checker>
<type>sizeof_mismatch</type>
<subtype>wrong_sizeof</subtype>
<file>/Users/dylanm/Projects/proftpd-1.3.5/modules/mod_core.c</file>
<function>core_sess_init</function>
<score>100</score>
<ordered>false</ordered>
<event>
<main>true</main>
<tag>suspicious_sizeof</tag>
<description>{CovLStrv2{{t{Passing argument {0} of type {1} and argument {2} to function {3} is suspicious.}{{code{&amp;session.total_files_out}}}{{code{unsigned int *}}}{{code{8UL /* sizeof (unsigned int *) */}}}{{code{pr_var_set}}}}}}</description>
<line>5997</line>
</event>
<event>
<remediation>true</remediation>
<tag>remediation</tag>
<description>{CovLStrv2{{t{Did you intend to use {0} instead of {1}?}{{code{sizeof (unsigned int)}}}{{code{sizeof (unsigned int *)}}}}}}</description>
<line>5997</line>
</event>
<extra>pr_var_set</extra>
<subcategory>wrong_sizeof</subcategory>
</error>
<error>
<domain>STATIC_C</domain>
<lang>C++</lang>
<checker>SIZEOF_MISMATCH</checker>
<type>sizeof_mismatch</type>
<subtype>wrong_sizeof</subtype>
<file>/Users/dylanm/Projects/proftpd-1.3.5/modules/mod_core.c</file>
<function>core_sess_init</function>
<score>100</score>
<ordered>false</ordered>
<event>
<main>true</main>
<tag>suspicious_sizeof</tag>
<description>{CovLStrv2{{t{Passing argument {0} of type {1} and argument {2} to function {3} is suspicious.}{{code{&amp;session.total_files_xfer}}}{{code{unsigned int *}}}{{code{8UL /* sizeof (unsigned int *) */}}}{{code{pr_var_set}}}}}}</description>
<line>6005</line>
</event>
<event>
<remediation>true</remediation>
<tag>remediation</tag>
<description>{CovLStrv2{{t{Did you intend to use {0} instead of {1}?}{{code{sizeof (unsigned int)}}}{{code{sizeof (unsigned int *)}}}}}}</description>
<line>6005</line>
</event>
<extra>pr_var_set</extra>
<subcategory>wrong_sizeof</subcategory>
</error>
<error>
<domain>STATIC_C</domain>
<lang>C++</lang>
<checker>SIZEOF_MISMATCH</checker>
<type>sizeof_mismatch</type>
<subtype>sizeof_punning</subtype>
<file>/Users/dylanm/Projects/proftpd-1.3.5/modules/mod_core.c</file>
<function>_chdir</function>
<score>100</score>
<ordered>false</ordered>
<event>
<main>true</main>
<tag>suspicious_sizeof</tag>
<description>{CovLStrv2{{t{Passing argument {0} to function {1} and then casting the return value to {2} is suspicious.}{{code{16UL /* sizeof (void **) * 2 */}}}{{code{pcalloc}}}{{code{void **}}}}{t{  In this particular case {0} happens to be equal to {1}, but this is not a portable assumption.}{{code{sizeof (void **)}}}{{code{sizeof (void *)}}}}}}</description>
<line>4714</line>
</event>
<event>
<remediation>true</remediation>
<tag>remediation</tag>
<description>{CovLStrv2{{t{Did you intend to use {0} instead of {1}?}{{code{sizeof (void *)}}}{{code{sizeof (void **)}}}}}}</description>
<line>4714</line>
</event>
<extra>pcalloc</extra>
<subcategory>sizeof_punning</subcategory>
</error>
